Metadata-Version: 2.1
Name: lib-python-pro
Version: 0.2
Summary: Módulo para exemplificar construção de projetos Python no curso PyTools
Home-page: https://github.com/victoraugusto6/libpythonpro
Author: Victor Augusto
Author-email: victor.augusto60@gmail.com
License: GNU AFFERO GENERAL PUBLIC LICENSE
Platform: UNKNOWN
Classifier: Development Status :: 2 - Pre-Alpha
Classifier: Environment :: Console
Classifier: Intended Audience :: Developers
Classifier: License :: OSI Approved :: GNU Affero General Public License v3 or later (AGPLv3+)
Classifier: Operating System :: OS Independent
Classifier: Programming Language :: Python
Classifier: Framework :: Pytest
